{
  "version": 3,
  "middleware": {
    "/": {
      "files": [
        "server/edge/chunks/_0d3699dc._.js",
        "server/edge/chunks/[root-of-the-server]__dc15d093._.js",
        "server/edge/chunks/edge-wrapper_594fdf6a.js"
      ],
      "name": "middleware",
      "page": "/",
      "matchers": [
        {
          "regexp": "^(?:\\/(_next\\/data\\/[^/]{1,}))?(?:\\/((?!api|_next\\/static|_next\\/image|favicon.ico).*))(\\\\.json)?[\\/#\\?]?$",
          "originalSource": "/((?!api|_next/static|_next/image|favicon.ico).*)"
        }
      ],
      "wasm": [],
      "assets": [],
      "env": {
        "__NEXT_BUILD_ID": "development",
        "NEXT_SERVER_ACTIONS_ENCRYPTION_KEY": "UOMR6nx7+STFbmvmqCQZnhvUX2/6GvSRYfaBi9CrKcs=",
        "__NEXT_PREVIEW_MODE_ID": "168337e77a1dbe7e905fa4475a053be8",
        "__NEXT_PREVIEW_MODE_ENCRYPTION_KEY": "4ecc582cb7f08f7f730f59f55c177bdf0343c02e5a284d2ec8017c13a2b5961c",
        "__NEXT_PREVIEW_MODE_SIGNING_KEY": "641a2428b553df2d4c12723501d446e867968ff683d4bf30ba7eebea9c5b3416"
      }
    }
  },
  "sortedMiddleware": [
    "/"
  ],
  "functions": {}
}